osslag/__init__.py
osslag/cli.py
osslag/distro/__init__.py
osslag/distro/debian.py
osslag/distro/fedora.py
osslag/metrics/__init__.py
osslag/metrics/malta.py
osslag/metrics/pvac.py
osslag/utils/__init__.py
osslag/utils/github_helper.py
osslag/utils/vcs.py
osslag-1.0.0.dist-info/WHEEL
osslag-1.0.0.dist-info/entry_points.txt
osslag-1.0.0.dist-info/METADATA
osslag-1.0.0.dist-info/RECORD
